bin2coe/__init__.py
bin2coe/cli.py
bin2coe/convert.py
bin2coe-1.1.1.dist-info/LICENSE.md
bin2coe-1.1.1.dist-info/METADATA
bin2coe-1.1.1.dist-info/WHEEL
bin2coe-1.1.1.dist-info/entry_points.txt
bin2coe-1.1.1.dist-info/top_level.txt
bin2coe-1.1.1.dist-info/RECORD
