Metadata-Version: 2.1
Name: bin2coe
Version: 1.1.1
Summary: A tool to convert binary files to COE files
Home-page: https://github.com/anishathalye/bin2coe
Author: Anish Athalye
Author-email: me@anishathalye.com
License: MIT
Keywords: xilinx coe bram
Classifier: Development Status :: 5 - Production/Stable
Classifier: Intended Audience :: Developers
Classifier: License :: OSI Approved :: MIT License
Classifier: Programming Language :: Python :: 3
Classifier: Topic :: Utilities
Requires-Python: >=3.4
License-File: LICENSE.md
